gnartz_webproxy/__init__.py
gnartz_webproxy/gnartz_webproxy.py
gnartz_webproxy/setup.py
gnartz_webproxy-0.2.0.data/scripts/webproxy
gnartz_webproxy-0.2.0.dist-info/LICENSE
gnartz_webproxy-0.2.0.dist-info/METADATA
gnartz_webproxy-0.2.0.dist-info/WHEEL
gnartz_webproxy-0.2.0.dist-info/top_level.txt
gnartz_webproxy-0.2.0.dist-info/RECORD
