Metadata-Version: 2.1
Name: gnartz-webproxy
Version: 0.2.0
Summary: A simple async web proxy.
Author: Jimmy Allen
Author-email: allenjsomb@gmail.com
Classifier: Programming Language :: Python :: 3
Classifier: License :: OSI Approved :: MIT License
Classifier: Operating System :: OS Independent
Requires-Python: >=3.10
License-File: LICENSE
Requires-Dist: aiohttp (==3.9.3)
Requires-Dist: click (==8.1.7)
